README.md
setup.cfg
setup.py
novel/__init__.py
novel/anomaly.py
novel/kernels.py
novel/utils.py
novel.egg-info/PKG-INFO
novel.egg-info/SOURCES.txt
novel.egg-info/dependency_links.txt
novel.egg-info/not-zip-safe
novel.egg-info/requires.txt
novel.egg-info/top_level.txt