Metadata-Version: 1.1
Name: novel
Version: 0.0.2
Summary: Novelty detection in Python
Home-page: https://github.com/tsitsimis/lemonpy
Author: Theodore Tsitsimis
Author-email: th.tsitsimis@gmail.com
License: MIT
Download-URL: https://github.com/tsitsimis/novel/archive/0.0.2.tar.gz
Keywords: novelty,svm,machine learning
Platform: UNKNOWN
Classifier: Development Status :: 3 - Alpha
Classifier: Intended Audience :: Developers
Classifier: Topic :: Software Development :: Build Tools
Classifier: License :: OSI Approved :: MIT License
Classifier: Programming Language :: Python :: 2.7
